easysoccerdata-0.0.8.dist-info/licenses/LICENSE
esd/__init__.py
esd/utils.py
esd/fbref/__init__.py
esd/fbref/client.py
esd/fbref/endpoints.py
esd/fbref/service.py
esd/fbref/utils.py
esd/fbref/exceptions/__init__.py
esd/fbref/types/__init__.py
esd/fbref/types/details.py
esd/fbref/types/match.py
esd/promiedos/__init__.py
esd/promiedos/client.py
esd/promiedos/endpoints.py
esd/promiedos/exceptions.py
esd/promiedos/service.py
esd/promiedos/types/__init__.py
esd/promiedos/types/color.py
esd/promiedos/types/event.py
esd/promiedos/types/league.py
esd/promiedos/types/match.py
esd/promiedos/types/match_events.py
esd/promiedos/types/match_stats.py
esd/promiedos/types/odds.py
esd/promiedos/types/players.py
esd/promiedos/types/scores.py
esd/promiedos/types/status.py
esd/promiedos/types/team.py
esd/promiedos/types/tournament.py
esd/promiedos/types/tvnetwork.py
esd/sofascore/__init__.py
esd/sofascore/client.py
esd/sofascore/endpoints.py
esd/sofascore/service.py
esd/sofascore/types/__init__.py
esd/sofascore/types/bracket.py
esd/sofascore/types/categories.py
esd/sofascore/types/color.py
esd/sofascore/types/comment.py
esd/sofascore/types/country.py
esd/sofascore/types/entity.py
esd/sofascore/types/event.py
esd/sofascore/types/incident.py
esd/sofascore/types/lineup.py
esd/sofascore/types/manager.py
esd/sofascore/types/match_stats.py
esd/sofascore/types/player.py
esd/sofascore/types/player_attributes.py
esd/sofascore/types/season.py
esd/sofascore/types/shot.py
esd/sofascore/types/standing.py
esd/sofascore/types/status.py
esd/sofascore/types/team.py
esd/sofascore/types/team_score.py
esd/sofascore/types/top.py
esd/sofascore/types/top_tournament_players.py
esd/sofascore/types/top_tournament_teams.py
esd/sofascore/types/tournament.py
esd/sofascore/types/transfer.py
easysoccerdata-0.0.8.dist-info/METADATA
easysoccerdata-0.0.8.dist-info/WHEEL
easysoccerdata-0.0.8.dist-info/top_level.txt
easysoccerdata-0.0.8.dist-info/RECORD
