Metadata-Version: 2.4
Name: EasySoccerData
Version: 0.0.8
Summary: A simple python package for extracting real-time soccer data from diverse online sources, providing essential statistics and insights.
Home-page: https://github.com/manucabral/EasySoccerData
Author: Manuel Cabral
License: GPL-3.0
Project-URL: Bug Tracker, https://github.com/manucabral/EasySoccerData/issues
Project-URL: Documentation, https://github.com/manucabral/EasySoccerData/blob/main/README.md
Project-URL: Source Code, https://github.com/manucabral/EasySoccerData/tree/main/esd
Keywords: fifa,ranking,soccer,data,soccerdata,football,worldcup,fifaranking,footballdata,europaleague,championsleague,scraper,webscraper,soccerstats,soccerstatistics,socceranalysis,footballstats,footballstatistics,footballanalysis,soccerapi,footballapi,soccerdatabase
Requires-Python: >=3.9
License-File: LICENSE
Requires-Dist: httpx==0.28.1
Dynamic: author
Dynamic: description
Dynamic: description-content-type
Dynamic: home-page
Dynamic: keywords
Dynamic: license
Dynamic: license-file
Dynamic: project-url
Dynamic: requires-dist
Dynamic: requires-python
Dynamic: summary
